[
  {
    "name": "TX-08",
    "TMIN": 73.04,
    "SNWD": 0
  },
  {
    "name": "TX-08",
    "TMIN": 51.08,
    "SNWD": 0
  },
  {
    "name": "TX-08",
    "TMIN": 71.96,
    "SNWD": 0
  },
  {
    "name": "TX-08",
    "TMIN": 73.04,
    "SNWD": 0
  },
  {
    "name": "TX-08",
    "TMIN": 75.92,
    "SNWD": 0
  },
  {
    "name": "TX-08",
    "TMIN": 71.06,
    "SNWD": 0
  },
  {
    "name": "TX-08",
    "TMIN": 77,
    "SNWD": 0
  },
  {
    "name": "TX-08",
    "TMIN": 75.02,
    "SNWD": 0
  },
  {
    "name": "TX-08",
    "TMIN": 73.94,
    "SNWD": 0
  },
  {
    "name": "TX-08",
    "TMIN": 80.06,
    "SNWD": 0
  },
  {
    "name": "TX-08",
    "TMIN": 77,
    "SNWD": 0
  },
  {
    "name": "TX-08",
    "TMIN": 73.04,
    "SNWD": 0
  },
  {
    "name": "TX-08",
    "TMIN": 75.92,
    "SNWD": 0
  },
  {
    "name": "TX-08",
    "TMIN": 75.92,
    "SNWD": 0
  },
  {
    "name": "TX-08",
    "TMIN": 75.02,
    "SNWD": 0
  },
  {
    "name": "TX-08",
    "TMIN": 75.02,
    "SNWD": 0
  },
  {
    "name": "TX-08",
    "TMIN": 78.98,
    "SNWD": 0
  },
  {
    "name": "TX-08",
    "TMIN": 75.02,
    "SNWD": 0
  },
  {
    "name": "TX-08",
    "TMIN": 66.02,
    "SNWD": 0
  },
  {
    "name": "TX-08",
    "TMIN": 73.94,
    "SNWD": 0
  },
  {
    "name": "TX-08",
    "TMIN": 75.02,
    "SNWD": 0
  },
  {
    "name": "TX-08",
    "TMIN": 80.06,
    "SNWD": 0
  },
  {
    "name": "TX-08",
    "TMIN": 73.04,
    "SNWD": 0
  },
  {
    "name": "TX-08",
    "TMIN": 71.06,
    "SNWD": 0
  },
  {
    "name": "TX-08",
    "TMIN": 69.08,
    "SNWD": 0
  },
  {
    "name": "TX-08",
    "TMIN": 71.06,
    "SNWD": 0
  },
  {
    "name": "TX-08",
    "TMIN": 75.92,
    "SNWD": 0
  },
  {
    "name": "TX-08",
    "TMIN": 78.98,
    "SNWD": 0
  },
  {
    "name": "TX-08",
    "TMIN": 75.02,
    "SNWD": 0
  },
  {
    "name": "TX-08",
    "TMIN": 78.98,
    "SNWD": 0
  },
  {
    "name": "MN-09",
    "TMIN": 51.98,
    "SNWD": 0
  },
  {
    "name": "MN-09",
    "TMIN": 60.08,
    "SNWD": 0
  },
  {
    "name": "MN-09",
    "TMIN": 51.98,
    "SNWD": 0
  },
  {
    "name": "MN-09",
    "TMIN": 48.92,
    "SNWD": 0
  },
  {
    "name": "MN-09",
    "TMIN": 62.06,
    "SNWD": 0
  },
  {
    "name": "MN-09",
    "TMIN": 57.02,
    "SNWD": 0
  },
  {
    "name": "MN-09",
    "TMIN": 44.96,
    "SNWD": 0
  },
  {
    "name": "MN-09",
    "TMIN": 42.98,
    "SNWD": 0
  },
  {
    "name": "MN-09",
    "TMIN": 64.94,
    "SNWD": 0
  },
  {
    "name": "MN-09",
    "TMIN": 62.06,
    "SNWD": 0
  },
  {
    "name": "MN-09",
    "TMIN": 55.94,
    "SNWD": 0
  },
  {
    "name": "MN-09",
    "TMIN": 66.92,
    "SNWD": 0
  },
  {
    "name": "MN-09",
    "TMIN": 42.98,
    "SNWD": 0
  },
  {
    "name": "MN-09",
    "TMIN": 46.94,
    "SNWD": 0
  },
  {
    "name": "MN-09",
    "TMIN": 64.04,
    "SNWD": 0
  },
  {
    "name": "MN-09",
    "TMIN": 46.94,
    "SNWD": 0
  },
  {
    "name": "MN-09",
    "TMIN": 51.98,
    "SNWD": 0
  },
  {
    "name": "MN-09",
    "TMIN": 50,
    "SNWD": 0
  },
  {
    "name": "MN-09",
    "TMIN": 48.02,
    "SNWD": 0
  },
  {
    "name": "MN-09",
    "TMIN": 60.98,
    "SNWD": 0
  },
  {
    "name": "MN-09",
    "TMIN": 48.02,
    "SNWD": 0
  },
  {
    "name": "MN-09",
    "TMIN": 0,
    "SNWD": 0
  },
  {
    "name": "MN-09",
    "TMIN": 44.06,
    "SNWD": 0
  },
  {
    "name": "MN-09",
    "TMIN": 50,
    "SNWD": 0
  },
  {
    "name": "MN-09",
    "TMIN": 46.94,
    "SNWD": 0
  },
  {
    "name": "MN-09",
    "TMIN": 55.94,
    "SNWD": 0
  },
  {
    "name": "MN-09",
    "TMIN": 55.94,
    "SNWD": 0
  },
  {
    "name": "MN-09",
    "TMIN": 53.96,
    "SNWD": 0
  },
  {
    "name": "MN-09",
    "TMIN": 48.02,
    "SNWD": 0
  },
  {
    "name": "MN-09",
    "TMIN": 62.06,
    "SNWD": 0
  },
  {
    "name": "CA-02",
    "SNWD": 25.98427,
    "TMIN": 44.96
  },
  {
    "name": "CA-02",
    "SNWD": 24.01576,
    "TMIN": 53.96
  },
  {
    "name": "CA-02",
    "SNWD": 24.01576,
    "TMIN": 46.94
  },
  {
    "name": "CA-02",
    "SNWD": 30.00002,
    "TMIN": 42.08
  },
  {
    "name": "CA-02",
    "SNWD": 0.98425,
    "TMIN": 20.12
  },
  {
    "name": "CA-02",
    "SNWD": 25.98427,
    "TMIN": 51.98
  },
  {
    "name": "CA-02",
    "SNWD": 14.01576,
    "TMIN": 7.16
  },
  {
    "name": "CA-02",
    "SNWD": 35.00002,
    "TMIN": 28.22
  },
  {
    "name": "CA-02",
    "SNWD": 34.01577,
    "TMIN": 31.1
  },
  {
    "name": "CA-02",
    "SNWD": 5,
    "TMIN": 21.2
  },
  {
    "name": "CA-02",
    "SNWD": 30.98427,
    "TMIN": 29.12
  },
  {
    "name": "CA-02",
    "SNWD": 7.99213,
    "TMIN": 21.2
  },
  {
    "name": "CA-02",
    "SNWD": 20.98426,
    "TMIN": 44.06
  },
  {
    "name": "CA-02",
    "SNWD": 20.98426,
    "TMIN": 42.98
  },
  {
    "name": "CA-02",
    "SNWD": 25.00001,
    "TMIN": 48.92
  },
  {
    "name": "CA-02",
    "TMIN": 29.12,
    "SNWD": 0
  },
  {
    "name": "CA-02",
    "TMIN": 53.96,
    "SNWD": 0
  },
  {
    "name": "CA-02",
    "TMIN": 46.94,
    "SNWD": 0
  },
  {
    "name": "CA-02",
    "TMIN": 28.22,
    "SNWD": 0
  },
  {
    "name": "CA-02",
    "TMIN": 44.96,
    "SNWD": 0
  },
  {
    "name": "CA-02",
    "TMIN": 35.06,
    "SNWD": 0
  },
  {
    "name": "CA-02",
    "TMIN": 41,
    "SNWD": 0
  },
  {
    "name": "CA-02",
    "TMIN": 53.96,
    "SNWD": 0
  },
  {
    "name": "CA-02",
    "TMIN": 39.02,
    "SNWD": 0
  },
  {
    "name": "CA-02",
    "TMIN": 55.04,
    "SNWD": 0
  },
  {
    "name": "CA-02",
    "TMIN": 42.08,
    "SNWD": 0
  },
  {
    "name": "CA-02",
    "TMIN": 60.98,
    "SNWD": 0
  },
  {
    "name": "CA-02",
    "TMIN": 27.14,
    "SNWD": 0
  },
  {
    "name": "CA-02",
    "TMIN": 55.04,
    "SNWD": 0
  },
  {
    "name": "CA-02",
    "TMIN": 41,
    "SNWD": 0
  },
  {
    "name": "IA-03",
    "SNWD": 5.11811,
    "TMIN": 21.2
  },
  {
    "name": "IA-03",
    "SNWD": 3.14961,
    "TMIN": 4.1
  },
  {
    "name": "IA-03",
    "SNWD": 1.1811,
    "TMIN": 28.04
  },
  {
    "name": "IA-03",
    "SNWD": 5.11811,
    "TMIN": 26.24
  },
  {
    "name": "IA-03",
    "SNWD": 9.05512,
    "TMIN": 35.06
  },
  {
    "name": "IA-03",
    "SNWD": 1.1811,
    "TMIN": 24.26
  },
  {
    "name": "IA-03",
    "SNWD": 3.14961,
    "TMIN": 7.16
  },
  {
    "name": "IA-03",
    "SNWD": 1.1811,
    "TMIN": 27.14
  },
  {
    "name": "IA-03",
    "SNWD": 3.14961,
    "TMIN": 11.12
  },
  {
    "name": "IA-03",
    "SNWD": 1.1811,
    "TMIN": 27.14
  },
  {
    "name": "IA-03",
    "SNWD": 3.14961,
    "TMIN": 26.24
  },
  {
    "name": "IA-03",
    "SNWD": 3.14961,
    "TMIN": -2.74
  },
  {
    "name": "IA-03",
    "SNWD": 1.1811,
    "TMIN": 5.18
  },
  {
    "name": "IA-03",
    "SNWD": 11.02363,
    "TMIN": 15.26
  },
  {
    "name": "IA-03",
    "SNWD": 3.14961,
    "TMIN": -1.84
  },
  {
    "name": "IA-03",
    "SNWD": 0,
    "TMIN": 29.12
  },
  {
    "name": "IA-03",
    "SNWD": 0,
    "TMIN": 46.04
  },
  {
    "name": "IA-03",
    "TMIN": 28.22,
    "SNWD": 0
  },
  {
    "name": "IA-03",
    "SNWD": 0,
    "TMIN": 30.2
  },
  {
    "name": "IA-03",
    "SNWD": 0,
    "TMIN": 28.22
  },
  {
    "name": "IA-03",
    "SNWD": 0,
    "TMIN": 28.22
  },
  {
    "name": "IA-03",
    "SNWD": 0,
    "TMIN": 46.04
  },
  {
    "name": "IA-03",
    "TMIN": 24.26,
    "SNWD": 0
  },
  {
    "name": "IA-03",
    "SNWD": 0,
    "TMIN": 46.04
  },
  {
    "name": "IA-03",
    "TMIN": 37.94,
    "SNWD": 0
  },
  {
    "name": "IA-03",
    "SNWD": 0,
    "TMIN": 24.26
  },
  {
    "name": "IA-03",
    "TMIN": 33.98,
    "SNWD": 0
  },
  {
    "name": "IA-03",
    "TMIN": 37.94,
    "SNWD": 0
  },
  {
    "name": "IA-03",
    "TMIN": 21.2,
    "SNWD": 0
  },
  {
    "name": "IA-03",
    "TMIN": 33.98,
    "SNWD": 0
  },
  {
    "name": "IN-01",
    "SNWD": 5.11811,
    "TMIN": 16.16
  },
  {
    "name": "IN-01",
    "SNWD": 5.11811,
    "TMIN": -1.84
  },
  {
    "name": "IN-01",
    "SNWD": 1.1811,
    "TMIN": 19.22
  },
  {
    "name": "IN-01",
    "SNWD": 3.14961,
    "TMIN": 6.26
  },
  {
    "name": "IN-01",
    "SNWD": 3.14961,
    "TMIN": 21.2
  },
  {
    "name": "IN-01",
    "SNWD": 5.11811,
    "TMIN": 9.14
  },
  {
    "name": "IN-01",
    "SNWD": 3.14961,
    "TMIN": 6.26
  },
  {
    "name": "IN-01",
    "SNWD": 1.96851,
    "TMIN": 1.22
  },
  {
    "name": "IN-01",
    "SNWD": 1.96851,
    "TMIN": 13.1
  },
  {
    "name": "IN-01",
    "SNWD": 1.1811,
    "TMIN": 33.98
  },
  {
    "name": "IN-01",
    "SNWD": 1.96851,
    "TMIN": 28.22
  },
  {
    "name": "IN-01",
    "SNWD": 3.14961,
    "TMIN": 11.12
  },
  {
    "name": "IN-01",
    "SNWD": 3.14961,
    "TMIN": 7.16
  },
  {
    "name": "IN-01",
    "SNWD": 3.14961,
    "TMIN": 8.24
  },
  {
    "name": "IN-01",
    "SNWD": 3.14961,
    "TMIN": 13.1
  },
  {
    "name": "IN-01",
    "TMIN": 28.22,
    "SNWD": 0
  },
  {
    "name": "IN-01",
    "TMIN": 10.94,
    "SNWD": 0
  },
  {
    "name": "IN-01",
    "TMIN": 20.12,
    "SNWD": 0
  },
  {
    "name": "IN-01",
    "TMIN": 28.04,
    "SNWD": 0
  },
  {
    "name": "IN-01",
    "SNWD": 0,
    "TMIN": 3.2
  },
  {
    "name": "IN-01",
    "TMIN": 23.18,
    "SNWD": 0
  },
  {
    "name": "IN-01",
    "SNWD": 0,
    "TMIN": 26.24
  },
  {
    "name": "IN-01",
    "TMIN": 12.2,
    "SNWD": 0
  },
  {
    "name": "IN-01",
    "TMIN": 19.22,
    "SNWD": 0
  },
  {
    "name": "IN-01",
    "TMIN": 1.94,
    "SNWD": 0
  },
  {
    "name": "IN-01",
    "TMIN": 16.16,
    "SNWD": 0
  },
  {
    "name": "IN-01",
    "TMIN": 7.16,
    "SNWD": 0
  },
  {
    "name": "IN-01",
    "TMIN": 33.08,
    "SNWD": 0
  },
  {
    "name": "IN-01",
    "TMIN": 20.12,
    "SNWD": 0
  },
  {
    "name": "IN-01",
    "TMIN": 4.1,
    "SNWD": 0
  },
  {
    "name": "KY-01",
    "SNWD": 1.1811,
    "TMIN": 16.16
  },
  {
    "name": "KY-01",
    "SNWD": 7.87402,
    "TMIN": 10.22
  },
  {
    "name": "KY-01",
    "SNWD": 2.99213,
    "TMIN": 26.24
  },
  {
    "name": "KY-01",
    "SNWD": 12.99213,
    "TMIN": 12.2
  },
  {
    "name": "KY-01",
    "SNWD": 1.96851,
    "TMIN": 6.26
  },
  {
    "name": "KY-01",
    "SNWD": 2.00788,
    "TMIN": 26.24
  },
  {
    "name": "KY-01",
    "SNWD": 1.1811,
    "TMIN": 18.14
  },
  {
    "name": "KY-01",
    "SNWD": 1.96851,
    "TMIN": 22.1
  },
  {
    "name": "KY-01",
    "SNWD": 3.14961,
    "TMIN": 13.1
  },
  {
    "name": "KY-01",
    "SNWD": 3.93701,
    "TMIN": 19.22
  },
  {
    "name": "KY-01",
    "SNWD": 1.96851,
    "TMIN": 14.18
  },
  {
    "name": "KY-01",
    "SNWD": 1.96851,
    "TMIN": 19.22
  },
  {
    "name": "KY-01",
    "SNWD": 1.96851,
    "TMIN": 22.1
  },
  {
    "name": "KY-01",
    "SNWD": 1.1811,
    "TMIN": 13.1
  },
  {
    "name": "KY-01",
    "SNWD": 1.96851,
    "TMIN": 7.16
  },
  {
    "name": "KY-01",
    "SNWD": 0,
    "TMIN": 11.12
  },
  {
    "name": "KY-01",
    "TMIN": 17.24,
    "SNWD": 0
  },
  {
    "name": "KY-01",
    "TMIN": 39.92,
    "SNWD": 0
  },
  {
    "name": "KY-01",
    "SNWD": 0,
    "TMIN": 28.22
  },
  {
    "name": "KY-01",
    "SNWD": 0,
    "TMIN": 19.22
  },
  {
    "name": "KY-01",
    "SNWD": 0,
    "TMIN": 8.24
  },
  {
    "name": "KY-01",
    "TMIN": 13.1,
    "SNWD": 0
  },
  {
    "name": "KY-01",
    "SNWD": 0,
    "TMIN": 31.1
  },
  {
    "name": "KY-01",
    "TMIN": 9.14,
    "SNWD": 0
  },
  {
    "name": "KY-01",
    "SNWD": 0,
    "TMIN": 28.22
  },
  {
    "name": "KY-01",
    "SNWD": 0,
    "TMIN": 26.24
  },
  {
    "name": "KY-01",
    "TMIN": 19.22,
    "SNWD": 0
  },
  {
    "name": "KY-01",
    "SNWD": 0,
    "TMIN": 31.1
  },
  {
    "name": "KY-01",
    "SNWD": 0,
    "TMIN": 44.96
  },
  {
    "name": "KY-01",
    "SNWD": 0,
    "TMIN": 29.12
  },
  {
    "name": "ID-11",
    "TMIN": 19.22,
    "SNWD": 0
  },
  {
    "name": "ID-11",
    "TMIN": 26.24,
    "SNWD": 0
  },
  {
    "name": "ID-11",
    "TMIN": 23.18,
    "SNWD": 0
  },
  {
    "name": "ID-11",
    "TMIN": 17.24,
    "SNWD": 0
  },
  {
    "name": "ID-11",
    "TMIN": 25.16,
    "SNWD": 0
  },
  {
    "name": "ID-11",
    "TMIN": 37.04,
    "SNWD": 0
  },
  {
    "name": "ID-11",
    "TMIN": 14.18,
    "SNWD": 0
  },
  {
    "name": "ID-11",
    "TMIN": 33.08,
    "SNWD": 0
  },
  {
    "name": "ID-11",
    "TMIN": 37.94,
    "SNWD": 0
  },
  {
    "name": "ID-11",
    "TMIN": 26.24,
    "SNWD": 0
  },
  {
    "name": "ID-11",
    "TMIN": 41,
    "SNWD": 0
  },
  {
    "name": "ID-11",
    "TMIN": 26.24,
    "SNWD": 0
  },
  {
    "name": "ID-11",
    "TMIN": 29.12,
    "SNWD": 0
  },
  {
    "name": "ID-11",
    "TMIN": 22.1,
    "SNWD": 0
  },
  {
    "name": "ID-11",
    "TMIN": 27.14,
    "SNWD": 0
  },
  {
    "name": "ID-11",
    "TMIN": 29.12,
    "SNWD": 0
  },
  {
    "name": "ID-11",
    "TMIN": 31.1,
    "SNWD": 0
  },
  {
    "name": "ID-11",
    "TMIN": 42.08,
    "SNWD": 0
  },
  {
    "name": "ID-11",
    "TMIN": 39.02,
    "SNWD": 0
  },
  {
    "name": "ID-11",
    "TMIN": 31.1,
    "SNWD": 0
  },
  {
    "name": "ID-11",
    "TMIN": 28.22,
    "SNWD": 0
  },
  {
    "name": "ID-11",
    "TMIN": 27.14,
    "SNWD": 0
  },
  {
    "name": "ID-11",
    "TMIN": 25.16,
    "SNWD": 0
  },
  {
    "name": "ID-11",
    "TMIN": 27.14,
    "SNWD": 0
  },
  {
    "name": "ID-11",
    "TMIN": 29.12,
    "SNWD": 0
  },
  {
    "name": "ID-11",
    "TMIN": 26.24,
    "SNWD": 0
  },
  {
    "name": "ID-11",
    "TMIN": 41,
    "SNWD": 0
  },
  {
    "name": "ID-11",
    "TMIN": 35.96,
    "SNWD": 0
  },
  {
    "name": "ID-11",
    "TMIN": 39.02,
    "SNWD": 0
  },
  {
    "name": "ID-11",
    "TMIN": 37.04,
    "SNWD": 0
  },
  {
    "name": "MO-04",
    "TMIN": 53.96,
    "SNWD": 0
  },
  {
    "name": "MO-04",
    "TMIN": 48.92,
    "SNWD": 0
  },
  {
    "name": "MO-04",
    "TMIN": 44.96,
    "SNWD": 0
  },
  {
    "name": "MO-04",
    "TMIN": 39.02,
    "SNWD": 0
  },
  {
    "name": "MO-04",
    "TMIN": 51.98,
    "SNWD": 0
  },
  {
    "name": "MO-04",
    "TMIN": 57.02,
    "SNWD": 0
  },
  {
    "name": "MO-04",
    "TMIN": 46.04,
    "SNWD": 0
  },
  {
    "name": "MO-04",
    "TMIN": 57.92,
    "SNWD": 0
  },
  {
    "name": "MO-04",
    "TMIN": 51.98,
    "SNWD": 0
  },
  {
    "name": "MO-04",
    "TMIN": 37.94,
    "SNWD": 0
  },
  {
    "name": "MO-04",
    "TMIN": 48.02,
    "SNWD": 0
  },
  {
    "name": "MO-04",
    "TMIN": 33.98,
    "SNWD": 0
  },
  {
    "name": "MO-04",
    "TMIN": 37.04,
    "SNWD": 0
  },
  {
    "name": "MO-04",
    "TMIN": 53.06,
    "SNWD": 0
  },
  {
    "name": "MO-04",
    "TMIN": 46.94,
    "SNWD": 0
  },
  {
    "name": "MO-04",
    "TMIN": 41,
    "SNWD": 0
  },
  {
    "name": "MO-04",
    "TMIN": 48.92,
    "SNWD": 0
  },
  {
    "name": "MO-04",
    "TMIN": 46.94,
    "SNWD": 0
  },
  {
    "name": "MO-04",
    "TMIN": 48.92,
    "SNWD": 0
  },
  {
    "name": "MO-04",
    "TMIN": 41,
    "SNWD": 0
  },
  {
    "name": "MO-04",
    "TMIN": 29.12,
    "SNWD": 0
  },
  {
    "name": "MO-04",
    "TMIN": 48.92,
    "SNWD": 0
  },
  {
    "name": "MO-04",
    "TMIN": 42.98,
    "SNWD": 0
  },
  {
    "name": "MO-04",
    "TMIN": 46.04,
    "SNWD": 0
  },
  {
    "name": "MO-04",
    "TMIN": 44.96,
    "SNWD": 0
  },
  {
    "name": "MO-04",
    "TMIN": 37.04,
    "SNWD": 0
  },
  {
    "name": "MO-04",
    "TMIN": 33.98,
    "SNWD": 0
  },
  {
    "name": "MO-04",
    "TMIN": 53.96,
    "SNWD": 0
  },
  {
    "name": "MO-04",
    "TMIN": 0,
    "SNWD": 0
  },
  {
    "name": "MO-04",
    "TMIN": 44.96,
    "SNWD": 0
  },
  {
    "name": "NV-11",
    "SNWD": 1.1811,
    "TMIN": 4.1
  },
  {
    "name": "NV-11",
    "SNWD": 3.14961,
    "TMIN": 3.2
  },
  {
    "name": "NV-11",
    "SNWD": 1.1811,
    "TMIN": 10.22
  },
  {
    "name": "NV-11",
    "SNWD": 1.1811,
    "TMIN": 5.18
  },
  {
    "name": "NV-11",
    "TMIN": 59,
    "SNWD": 0
  },
  {
    "name": "NV-11",
    "TMIN": 46.04,
    "SNWD": 0
  },
  {
    "name": "NV-11",
    "TMIN": 21.2,
    "SNWD": 0
  },
  {
    "name": "NV-11",
    "TMIN": 46.04,
    "SNWD": 0
  },
  {
    "name": "NV-11",
    "TMIN": 37.94,
    "SNWD": 0
  },
  {
    "name": "NV-11",
    "TMIN": 53.06,
    "SNWD": 0
  },
  {
    "name": "NV-11",
    "TMIN": 26.24,
    "SNWD": 0
  },
  {
    "name": "NV-11",
    "TMIN": 59,
    "SNWD": 0
  },
  {
    "name": "NV-11",
    "TMIN": 0,
    "SNWD": 0
  },
  {
    "name": "NV-11",
    "TMIN": 28.22,
    "SNWD": 0
  },
  {
    "name": "NV-11",
    "TMIN": 22.1,
    "SNWD": 0
  },
  {
    "name": "NV-11",
    "TMIN": 30.2,
    "SNWD": 0
  },
  {
    "name": "NV-11",
    "TMIN": 33.08,
    "SNWD": 0
  },
  {
    "name": "NV-11",
    "SNWD": 0,
    "TMIN": 27.14
  },
  {
    "name": "NV-11",
    "SNWD": 0,
    "TMIN": 22.1
  },
  {
    "name": "NV-11",
    "TMIN": 30.2,
    "SNWD": 0
  },
  {
    "name": "NV-11",
    "TMIN": 25.16,
    "SNWD": 0
  },
  {
    "name": "NV-11",
    "SNWD": 0,
    "TMIN": 16.16
  },
  {
    "name": "NV-11",
    "TMIN": 0,
    "SNWD": 0
  },
  {
    "name": "NV-11",
    "TMIN": 23.18,
    "SNWD": 0
  },
  {
    "name": "NV-11",
    "TMIN": 53.06,
    "SNWD": 0
  },
  {
    "name": "NV-11",
    "TMIN": 15.26,
    "SNWD": 0
  },
  {
    "name": "NV-11",
    "TMIN": 31.1,
    "SNWD": 0
  },
  {
    "name": "NV-11",
    "TMIN": 28.22,
    "SNWD": 0
  },
  {
    "name": "NV-11",
    "SNWD": 0,
    "TMIN": 29.12
  },
  {
    "name": "NV-11",
    "TMIN": 33.08,
    "SNWD": 0
  },
  {
    "name": "ND-04",
    "TMIN": 21.2,
    "SNWD": 0
  },
  {
    "name": "ND-04",
    "TMIN": 24.26,
    "SNWD": 0
  },
  {
    "name": "ND-04",
    "TMIN": 35.06,
    "SNWD": 0
  },
  {
    "name": "ND-04",
    "TMIN": 16.16,
    "SNWD": 0
  },
  {
    "name": "ND-04",
    "TMIN": 42.08,
    "SNWD": 0
  },
  {
    "name": "ND-04",
    "TMIN": 39.92,
    "SNWD": 0
  },
  {
    "name": "ND-04",
    "TMIN": 46.94,
    "SNWD": 0
  },
  {
    "name": "ND-04",
    "TMIN": 21.2,
    "SNWD": 0
  },
  {
    "name": "ND-04",
    "TMIN": 0,
    "SNWD": 0
  },
  {
    "name": "ND-04",
    "TMIN": 33.98,
    "SNWD": 0
  },
  {
    "name": "ND-04",
    "TMIN": 33.98,
    "SNWD": 0
  },
  {
    "name": "ND-04",
    "TMIN": 0,
    "SNWD": 0
  },
  {
    "name": "ND-04",
    "TMIN": 33.08,
    "SNWD": 0
  },
  {
    "name": "ND-04",
    "TMIN": 37.04,
    "SNWD": 0
  },
  {
    "name": "ND-04",
    "TMIN": 35.06,
    "SNWD": 0
  },
  {
    "name": "ND-04",
    "TMIN": 19.22,
    "SNWD": 0
  },
  {
    "name": "ND-04",
    "TMIN": 22.1,
    "SNWD": 0
  },
  {
    "name": "ND-04",
    "TMIN": 21.2,
    "SNWD": 0
  },
  {
    "name": "ND-04",
    "TMIN": 42.98,
    "SNWD": 0
  },
  {
    "name": "ND-04",
    "TMIN": 33.98,
    "SNWD": 0
  },
  {
    "name": "ND-04",
    "TMIN": 33.98,
    "SNWD": 0
  },
  {
    "name": "ND-04",
    "TMIN": 39.02,
    "SNWD": 0
  },
  {
    "name": "ND-04",
    "TMIN": 33.08,
    "SNWD": 0
  },
  {
    "name": "ND-04",
    "TMIN": 23.18,
    "SNWD": 0
  },
  {
    "name": "ND-04",
    "TMIN": 46.04,
    "SNWD": 0
  },
  {
    "name": "ND-04",
    "TMIN": 28.22,
    "SNWD": 0
  },
  {
    "name": "ND-04",
    "TMIN": 30.2,
    "SNWD": 0
  },
  {
    "name": "ND-04",
    "TMIN": 42.08,
    "SNWD": 0
  },
  {
    "name": "ND-04",
    "TMIN": 30.2,
    "SNWD": 0
  },
  {
    "name": "ND-04",
    "TMIN": 0,
    "SNWD": 0
  }
]