[
  {
    "name": "AL-06",
    "WDF5": 50,
    "WSF5": 10.06623
  },
  {
    "name": "AL-06",
    "WDF5": 230,
    "WSF5": 14.09272
  },
  {
    "name": "AL-06",
    "WDF5": 330,
    "WSF5": 18.11921
  },
  {
    "name": "NY-01",
    "WDF5": 300,
    "WSF5": 14.09272
  },
  {
    "name": "NY-01",
    "WDF5": 190,
    "WSF5": 25.9485
  },
  {
    "name": "NY-01",
    "WDF5": 270,
    "WSF5": 46.97574
  },
  {
    "name": "GA-05",
    "WDF5": 280,
    "WSF5": 14.9875
  },
  {
    "name": "GA-05",
    "WDF5": 70,
    "WSF5": 12.97425
  },
  {
    "name": "GA-05",
    "WDF5": 340,
    "WSF5": 12.07948
  },
  {
    "name": "LA-09",
    "WDF5": 350,
    "WSF5": 17.00074
  },
  {
    "name": "LA-09",
    "WDF5": 160,
    "WSF5": 17.00074
  },
  {
    "name": "LA-09",
    "WDF5": 120,
    "WSF5": 12.97425
  },
  {
    "name": "PA-07",
    "WDF5": 170,
    "WSF5": 14.9875
  },
  {
    "name": "PA-07",
    "WDF5": 350,
    "WSF5": 27.96175
  },
  {
    "name": "PA-07",
    "WDF5": 360,
    "WSF5": 14.9875
  },
  {
    "name": "CA-06",
    "WDF5": 330,
    "WSF5": 14.09272
  },
  {
    "name": "CA-06",
    "WDF5": 160,
    "WSF5": 19.90877
  },
  {
    "name": "CA-06",
    "WDF5": 230,
    "WSF5": 17.00074
  },
  {
    "name": "SC-11",
    "WDF5": 260,
    "WSF5": 36.01473
  },
  {
    "name": "SC-11",
    "WDF5": 340,
    "WSF5": 10.06623
  },
  {
    "name": "SC-11",
    "WDF5": 40,
    "WSF5": 16.10597
  },
  {
    "name": "OR-11",
    "WDF5": 90,
    "WSF5": 27.06697
  },
  {
    "name": "OR-11",
    "WDF5": 190,
    "WSF5": 29.08022
  },
  {
    "name": "OR-11",
    "WDF5": 260,
    "WSF5": 21.92201
  },
  {
    "name": "MT-05",
    "WDF5": 290,
    "WSF5": 40.04123
  },
  {
    "name": "MT-05",
    "WDF5": 350,
    "WSF5": 23.04048
  },
  {
    "name": "MT-05",
    "WDF5": 360,
    "WSF5": 23.04048
  },
  {
    "name": "MD-04",
    "WDF5": 30,
    "WSF5": 23.04048
  },
  {
    "name": "MD-04",
    "WDF5": 170,
    "WSF5": 18.11921
  },
  {
    "name": "MD-04",
    "WDF5": 30,
    "WSF5": 21.92201
  },
  {
    "name": "WV-01",
    "WDF5": 140,
    "WSF5": 23.04048
  },
  {
    "name": "WV-01",
    "WDF5": 270,
    "WSF5": 51.00223
  },
  {
    "name": "WV-01",
    "WDF5": 330,
    "WSF5": 27.96175
  },
  {
    "name": "WY-04",
    "WDF5": 310,
    "WSF5": 40.936
  },
  {
    "name": "WY-04",
    "WDF5": 260,
    "WSF5": 38.02798
  },
  {
    "name": "WY-04",
    "WDF5": 160,
    "WSF5": 29.08022
  },
  {
    "name": "IN-12",
    "WDF5": 280,
    "WSF5": 33.10671
  },
  {
    "name": "IN-12",
    "WDF5": 190,
    "WSF5": 31.09347
  },
  {
    "name": "IN-12",
    "WDF5": 310,
    "WSF5": 25.05373
  },
  {
    "name": "UT-02",
    "WDF5": 350,
    "WSF5": 29.08022
  },
  {
    "name": "UT-02",
    "WDF5": 190,
    "WSF5": 8.94776
  },
  {
    "name": "UT-02",
    "WDF5": 40,
    "WSF5": 12.97425
  },
  {
    "name": "IL-11",
    "WDF5": 240,
    "WSF5": 27.96175
  },
  {
    "name": "IL-11",
    "WDF5": 310,
    "WSF5": 46.97574
  },
  {
    "name": "IL-11",
    "WDF5": 270,
    "WSF5": 42.05447
  },
  {
    "name": "OK-01",
    "WDF5": 330,
    "WSF5": 44.06772
  },
  {
    "name": "OK-01",
    "WDF5": 170,
    "WSF5": 16.10597
  },
  {
    "name": "OK-01",
    "WDF5": 190,
    "WSF5": 34.00149
  },
  {
    "name": "NV-03",
    "WDF5": 10,
    "WSF5": 19.90877
  },
  {
    "name": "NV-03",
    "WDF5": 10,
    "WSF5": 25.05373
  },
  {
    "name": "NV-03",
    "WDF5": 170,
    "WSF5": 50.10746
  },
  {
    "name": "HI-08",
    "WDF5": 60,
    "WSF5": 36.01473
  },
  {
    "name": "HI-08",
    "WDF5": 60,
    "WSF5": 34.00149
  },
  {
    "name": "HI-08",
    "WDF5": 70,
    "WSF5": 31.98824
  },
  {
    "name": "ND-01",
    "WDF5": 310,
    "WSF5": 33.10671
  },
  {
    "name": "ND-01",
    "WDF5": 290,
    "WSF5": 23.04048
  },
  {
    "name": "ND-01",
    "WDF5": 130,
    "WSF5": 19.01399
  },
  {
    "name": "MS-10",
    "WDF5": 190,
    "WSF5": 21.92201
  },
  {
    "name": "MS-10",
    "WDF5": 350,
    "WSF5": 23.93526
  },
  {
    "name": "MS-10",
    "WDF5": 120,
    "WSF5": 21.92201
  }
]