[
  {
    "name": "TX-03",
    "PRCP": 0,
    "TMIN": 42.98
  },
  {
    "name": "TX-03",
    "PRCP": 0,
    "TMIN": 35.96
  },
  {
    "name": "TX-03",
    "PRCP": 0,
    "TMIN": 51.08
  },
  {
    "name": "CO-08",
    "PRCP": 0.07087,
    "TMIN": 53.06
  },
  {
    "name": "CO-08",
    "PRCP": 0.03937,
    "TMIN": 50
  },
  {
    "name": "CO-08",
    "PRCP": 0.07874,
    "TMIN": 62.06
  },
  {
    "name": "AL-11",
    "PRCP": 0,
    "TMIN": 44.96
  },
  {
    "name": "AL-11",
    "PRCP": 0,
    "TMIN": 27.14
  },
  {
    "name": "AL-11",
    "PRCP": 0,
    "TMIN": 60.98
  },
  {
    "name": "NY-05",
    "PRCP": 0.20866,
    "TMIN": 35.96
  },
  {
    "name": "NY-05",
    "PRCP": 0,
    "TMIN": 66.02
  },
  {
    "name": "NY-05",
    "PRCP": 0.01181,
    "TMIN": 48.92
  },
  {
    "name": "NM-01",
    "PRCP": 0,
    "TMIN": 0
  },
  {
    "name": "NM-01",
    "PRCP": 0.0315,
    "TMIN": 28.22
  },
  {
    "name": "NM-01",
    "PRCP": 0.07874,
    "TMIN": 27.14
  },
  {
    "name": "CA-05",
    "PRCP": 0,
    "TMIN": 57.02
  },
  {
    "name": "CA-05",
    "PRCP": 0,
    "TMIN": 53.06
  },
  {
    "name": "CA-05",
    "PRCP": 0,
    "TMIN": 53.96
  },
  {
    "name": "IA-08",
    "PRCP": 0.94882,
    "TMIN": 64.04
  },
  {
    "name": "IA-08",
    "PRCP": 0.22835,
    "TMIN": 66.92
  },
  {
    "name": "IA-08",
    "PRCP": 0,
    "TMIN": 59
  },
  {
    "name": "AK-05",
    "PRCP": 0,
    "TMIN": 33.08
  },
  {
    "name": "AK-05",
    "PRCP": 0,
    "TMIN": 31.1
  },
  {
    "name": "AK-05",
    "PRCP": 0,
    "TMIN": 31.1
  },
  {
    "name": "NJ-08",
    "PRCP": 0,
    "TMIN": 57.02
  },
  {
    "name": "NJ-08",
    "PRCP": 0,
    "TMIN": 64.94
  },
  {
    "name": "NJ-08",
    "PRCP": 0,
    "TMIN": 73.94
  },
  {
    "name": "VA-07",
    "PRCP": 0,
    "TMIN": 66.02
  },
  {
    "name": "VA-07",
    "PRCP": 0.0315,
    "TMIN": 73.04
  },
  {
    "name": "VA-07",
    "PRCP": 0.96063,
    "TMIN": 69.08
  },
  {
    "name": "NH-10",
    "PRCP": 0,
    "TMIN": 31.1
  },
  {
    "name": "NH-10",
    "PRCP": 0,
    "TMIN": 44.06
  },
  {
    "name": "NH-10",
    "PRCP": 0.6811,
    "TMIN": 37.04
  },
  {
    "name": "MA-09",
    "TMIN": 48.02,
    "PRCP": 0
  },
  {
    "name": "MA-09",
    "PRCP": 0,
    "TMIN": 62.96
  },
  {
    "name": "MA-09",
    "PRCP": 0.25984,
    "TMIN": 66.02
  },
  {
    "name": "WY-10",
    "PRCP": 0,
    "TMIN": 46.94
  },
  {
    "name": "WY-10",
    "PRCP": 0,
    "TMIN": 30.2
  },
  {
    "name": "WY-10",
    "PRCP": 0,
    "TMIN": 30.2
  },
  {
    "name": "AR-10",
    "PRCP": 0,
    "TMIN": 46.04
  },
  {
    "name": "AR-10",
    "PRCP": 0,
    "TMIN": 50
  },
  {
    "name": "AR-10",
    "PRCP": 0.14173,
    "TMIN": 62.06
  },
  {
    "name": "CT-09",
    "PRCP": 0.07874,
    "TMIN": 71.06
  },
  {
    "name": "CT-09",
    "PRCP": 0,
    "TMIN": 71.96
  },
  {
    "name": "CT-09",
    "PRCP": 0.01181,
    "TMIN": 48.92
  },
  {
    "name": "TN-06",
    "PRCP": 0,
    "TMIN": 69.08
  },
  {
    "name": "TN-06",
    "PRCP": 0,
    "TMIN": 75.02
  },
  {
    "name": "TN-06",
    "PRCP": 1.03937,
    "TMIN": 68
  },
  {
    "name": "UT-06",
    "PRCP": 0,
    "TMIN": 53.96
  },
  {
    "name": "UT-06",
    "PRCP": 0,
    "TMIN": 62.06
  },
  {
    "name": "UT-06",
    "PRCP": 0,
    "TMIN": 59
  },
  {
    "name": "MO-10",
    "PRCP": 0,
    "TMIN": 69.08
  },
  {
    "name": "MO-10",
    "PRCP": 0,
    "TMIN": 50
  },
  {
    "name": "MO-10",
    "PRCP": 0,
    "TMIN": 42.98
  },
  {
    "name": "AZ-12",
    "PRCP": 0.07874,
    "TMIN": 33.08
  },
  {
    "name": "AZ-12",
    "PRCP": 0.11811,
    "TMIN": 0
  },
  {
    "name": "AZ-12",
    "PRCP": 0.03937,
    "TMIN": 57.02
  },
  {
    "name": "ND-07",
    "PRCP": 1.37008,
    "TMIN": 57.02
  },
  {
    "name": "ND-07",
    "PRCP": 0,
    "TMIN": 53.06
  },
  {
    "name": "ND-07",
    "PRCP": 0,
    "TMIN": 57.02
  }
]