[
  {
    "name": "AL-09",
    "PRCP": 0,
    "TMIN": 71.96
  },
  {
    "name": "AL-09",
    "PRCP": 0.11024,
    "TMIN": 71.06
  },
  {
    "name": "AL-09",
    "PRCP": 0.03937,
    "TMIN": 75.02
  },
  {
    "name": "PA-07",
    "PRCP": 0,
    "TMIN": 77
  },
  {
    "name": "PA-07",
    "PRCP": 0.8189,
    "TMIN": 73.04
  },
  {
    "name": "PA-07",
    "PRCP": 0,
    "TMIN": 59
  },
  {
    "name": "ID-07",
    "PRCP": 0,
    "TMIN": 57.02
  },
  {
    "name": "ID-07",
    "PRCP": 0,
    "TMIN": 51.98
  },
  {
    "name": "ID-07",
    "PRCP": 0,
    "TMIN": 62.96
  }
]