[
  {
    "name": "VT-10",
    "AWND": 15.21119,
    "TMAX": 60.98
  },
  {
    "name": "VT-10",
    "AWND": 2.23694,
    "TMAX": 57.92
  },
  {
    "name": "VT-10",
    "AWND": 1.11847,
    "TMAX": 62.06
  },
  {
    "name": "VT-10",
    "AWND": 10.96101,
    "TMAX": 53.96
  },
  {
    "name": "VT-10",
    "AWND": 1.34216,
    "TMAX": 66.92
  },
  {
    "name": "VT-10",
    "AWND": 2.90802,
    "TMAX": 75.02
  },
  {
    "name": "VT-10",
    "AWND": 9.84254,
    "TMAX": 46.04
  },
  {
    "name": "VT-10",
    "AWND": 5.36866,
    "TMAX": 42.08
  },
  {
    "name": "VT-10",
    "AWND": 0.89478,
    "TMAX": 66.92
  },
  {
    "name": "VT-10",
    "AWND": 5.36866,
    "TMAX": 57.02
  },
  {
    "name": "VT-10",
    "AWND": 11.63209,
    "TMAX": 71.06
  },
  {
    "name": "VT-10",
    "AWND": 10.28992,
    "TMAX": 35.96
  },
  {
    "name": "VT-10",
    "AWND": 8.50037,
    "TMAX": 53.96
  },
  {
    "name": "VT-10",
    "AWND": 1.78955,
    "TMAX": 57.02
  },
  {
    "name": "VT-10",
    "AWND": 6.48713,
    "TMAX": 55.04
  },
  {
    "name": "VT-10",
    "AWND": 5.36866,
    "TMAX": 51.08
  },
  {
    "name": "VT-10",
    "AWND": 12.30317,
    "TMAX": 46.94
  },
  {
    "name": "VT-10",
    "AWND": 1.11847,
    "TMAX": 55.94
  },
  {
    "name": "VT-10",
    "AWND": 4.47388,
    "TMAX": 55.94
  },
  {
    "name": "VT-10",
    "AWND": 2.90802,
    "TMAX": 75.92
  },
  {
    "name": "VT-10",
    "AWND": 9.61884,
    "TMAX": 53.06
  },
  {
    "name": "VT-10",
    "AWND": 7.3819,
    "TMAX": 46.04
  },
  {
    "name": "VT-10",
    "AWND": 1.78955,
    "TMAX": 60.98
  },
  {
    "name": "VT-10",
    "AWND": 6.48713,
    "TMAX": 73.94
  },
  {
    "name": "VT-10",
    "AWND": 2.90802,
    "TMAX": 64.04
  },
  {
    "name": "VT-10",
    "AWND": 7.3819,
    "TMAX": 48.02
  },
  {
    "name": "VT-10",
    "AWND": 6.71082,
    "TMAX": 69.08
  },
  {
    "name": "VT-10",
    "AWND": 1.56586,
    "TMAX": 64.94
  },
  {
    "name": "VT-10",
    "AWND": 0.67108,
    "TMAX": 62.06
  },
  {
    "name": "VT-10",
    "AWND": 9.61884,
    "TMAX": 51.08
  },
  {
    "name": "ID-04",
    "AWND": 8.72407,
    "TMAX": 66.92
  },
  {
    "name": "ID-04",
    "AWND": 3.5791,
    "TMAX": 71.06
  },
  {
    "name": "ID-04",
    "AWND": 3.5791,
    "TMAX": 73.04
  },
  {
    "name": "ID-04",
    "AWND": 10.06623,
    "TMAX": 66.92
  },
  {
    "name": "ID-04",
    "AWND": 2.23694,
    "TMAX": 57.02
  },
  {
    "name": "ID-04",
    "AWND": 14.9875,
    "TMAX": 53.96
  },
  {
    "name": "ID-04",
    "AWND": 3.5791,
    "TMAX": 59
  },
  {
    "name": "ID-04",
    "AWND": 6.71082,
    "TMAX": 82.04
  },
  {
    "name": "ID-04",
    "AWND": 8.94776,
    "TMAX": 68
  },
  {
    "name": "ID-04",
    "AWND": 9.61884,
    "TMAX": 57.02
  },
  {
    "name": "ID-04",
    "AWND": 8.94776,
    "TMAX": 59
  },
  {
    "name": "ID-04",
    "AWND": 5.59235,
    "TMAX": 64.94
  },
  {
    "name": "ID-04",
    "AWND": 14.54011,
    "TMAX": 48.92
  },
  {
    "name": "ID-04",
    "AWND": 11.63209,
    "TMAX": 62.96
  },
  {
    "name": "ID-04",
    "AWND": 4.92127,
    "TMAX": 64.04
  },
  {
    "name": "ID-04",
    "AWND": 8.05298,
    "TMAX": 66.02
  },
  {
    "name": "ID-04",
    "AWND": 16.10597,
    "TMAX": 78.08
  },
  {
    "name": "ID-04",
    "AWND": 12.30317,
    "TMAX": 44.06
  },
  {
    "name": "ID-04",
    "AWND": 14.09272,
    "TMAX": 57.92
  },
  {
    "name": "ID-04",
    "AWND": 3.8028,
    "TMAX": 60.08
  },
  {
    "name": "ID-04",
    "AWND": 7.15821,
    "TMAX": 60.98
  },
  {
    "name": "ID-04",
    "AWND": 4.69757,
    "TMAX": 66.02
  },
  {
    "name": "ID-04",
    "AWND": 8.50037,
    "TMAX": 59
  },
  {
    "name": "ID-04",
    "AWND": 4.25019,
    "TMAX": 77
  },
  {
    "name": "ID-04",
    "AWND": 6.93451,
    "TMAX": 60.08
  },
  {
    "name": "ID-04",
    "AWND": 5.59235,
    "TMAX": 60.08
  },
  {
    "name": "ID-04",
    "AWND": 16.10597,
    "TMAX": 55.04
  },
  {
    "name": "ID-04",
    "AWND": 8.27668,
    "TMAX": 66.92
  },
  {
    "name": "ID-04",
    "AWND": 13.86903,
    "TMAX": 82.94
  },
  {
    "name": "ID-04",
    "AWND": 3.5791,
    "TMAX": 82.04
  },
  {
    "name": "HI-07",
    "AWND": 7.6056,
    "TMAX": 84.92
  },
  {
    "name": "HI-07",
    "AWND": 17.22444,
    "TMAX": 87.08
  },
  {
    "name": "HI-07",
    "AWND": 8.27668,
    "TMAX": 89.96
  },
  {
    "name": "HI-07",
    "AWND": 8.94776,
    "TMAX": 87.08
  },
  {
    "name": "HI-07",
    "AWND": 12.30317,
    "TMAX": 84.02
  },
  {
    "name": "HI-07",
    "AWND": 20.35615,
    "TMAX": 89.96
  },
  {
    "name": "HI-07",
    "AWND": 8.05298,
    "TMAX": 84.92
  },
  {
    "name": "HI-07",
    "AWND": 7.82929,
    "TMAX": 91.04
  },
  {
    "name": "HI-07",
    "AWND": 8.50037,
    "TMAX": 87.98
  },
  {
    "name": "HI-07",
    "AWND": 14.9875,
    "TMAX": 86
  },
  {
    "name": "HI-07",
    "AWND": 14.31642,
    "TMAX": 84.92
  },
  {
    "name": "HI-07",
    "AWND": 12.07948,
    "TMAX": 87.08
  },
  {
    "name": "HI-07",
    "AWND": 6.93451,
    "TMAX": 93.02
  },
  {
    "name": "HI-07",
    "AWND": 8.05298,
    "TMAX": 89.06
  },
  {
    "name": "HI-07",
    "AWND": 15.43489,
    "TMAX": 91.04
  },
  {
    "name": "HI-07",
    "AWND": 18.5666,
    "TMAX": 87.98
  },
  {
    "name": "HI-07",
    "AWND": 15.88227,
    "TMAX": 82.94
  },
  {
    "name": "HI-07",
    "AWND": 14.09272,
    "TMAX": 82.94
  },
  {
    "name": "HI-07",
    "AWND": 8.27668,
    "TMAX": 91.94
  },
  {
    "name": "HI-07",
    "AWND": 11.85578,
    "TMAX": 89.06
  },
  {
    "name": "HI-07",
    "AWND": 6.48713,
    "TMAX": 87.98
  },
  {
    "name": "HI-07",
    "AWND": 10.51362,
    "TMAX": 89.06
  },
  {
    "name": "HI-07",
    "AWND": 7.82929,
    "TMAX": 87.98
  },
  {
    "name": "HI-07",
    "AWND": 5.36866,
    "TMAX": 86
  },
  {
    "name": "HI-07",
    "AWND": 16.55336,
    "TMAX": 87.98
  },
  {
    "name": "HI-07",
    "AWND": 5.14496,
    "TMAX": 91.04
  },
  {
    "name": "HI-07",
    "AWND": 19.68507,
    "TMAX": 82.04
  },
  {
    "name": "HI-07",
    "AWND": 7.15821,
    "TMAX": 86
  },
  {
    "name": "HI-07",
    "AWND": 10.06623,
    "TMAX": 86
  },
  {
    "name": "HI-07",
    "AWND": 6.03974,
    "TMAX": 87.08
  }
]