[
  {
    "name": "MI-12",
    "TMIN": 33.98,
    "WDF5": 190
  },
  {
    "name": "MI-12",
    "TMIN": 31.1,
    "WDF5": 310
  },
  {
    "name": "MI-12",
    "TMIN": 0,
    "WDF5": 120
  },
  {
    "name": "MI-12",
    "TMIN": 16.16,
    "WDF5": 240
  },
  {
    "name": "MI-12",
    "TMIN": 33.08,
    "WDF5": 270
  },
  {
    "name": "MI-12",
    "TMIN": 25.16,
    "WDF5": 250
  },
  {
    "name": "MI-12",
    "TMIN": 35.06,
    "WDF5": 260
  },
  {
    "name": "MI-12",
    "TMIN": 16.16,
    "WDF5": 150
  },
  {
    "name": "MI-12",
    "TMIN": 2.12,
    "WDF5": 200
  },
  {
    "name": "MI-12",
    "TMIN": 33.98,
    "WDF5": 270
  },
  {
    "name": "MI-12",
    "TMIN": 27.14,
    "WDF5": 280
  },
  {
    "name": "MI-12",
    "TMIN": 37.04,
    "WDF5": 300
  },
  {
    "name": "MI-12",
    "TMIN": 25.16,
    "WDF5": 220
  },
  {
    "name": "MI-12",
    "TMIN": 31.1,
    "WDF5": 250
  },
  {
    "name": "MI-12",
    "TMIN": 24.26,
    "WDF5": 320
  },
  {
    "name": "MI-12",
    "TMIN": 19.22,
    "WDF5": 150
  },
  {
    "name": "MI-12",
    "TMIN": 33.98,
    "WDF5": 270
  },
  {
    "name": "MI-12",
    "TMIN": 33.08,
    "WDF5": 300
  },
  {
    "name": "MI-12",
    "TMIN": 18.14,
    "WDF5": 250
  },
  {
    "name": "MI-12",
    "TMIN": 22.1,
    "WDF5": 150
  },
  {
    "name": "MI-12",
    "TMIN": 31.1,
    "WDF5": 290
  },
  {
    "name": "MI-12",
    "TMIN": 24.26,
    "WDF5": 190
  },
  {
    "name": "MI-12",
    "TMIN": 8.24,
    "WDF5": 350
  },
  {
    "name": "MI-12",
    "TMIN": 22.1,
    "WDF5": 320
  },
  {
    "name": "MI-12",
    "TMIN": 23.18,
    "WDF5": 250
  },
  {
    "name": "MI-12",
    "TMIN": -4.9,
    "WDF5": 200
  },
  {
    "name": "MI-12",
    "TMIN": 9.14,
    "WDF5": 320
  },
  {
    "name": "MI-12",
    "TMIN": 0,
    "WDF5": 130
  },
  {
    "name": "MI-12",
    "TMIN": 8.24,
    "WDF5": 340
  },
  {
    "name": "MI-12",
    "TMIN": 28.22,
    "WDF5": 260
  },
  {
    "name": "IN-08",
    "TMIN": 69.08,
    "WDF5": 100
  },
  {
    "name": "IN-08",
    "TMIN": 73.04,
    "WDF5": 280
  },
  {
    "name": "IN-08",
    "TMIN": 62.06,
    "WDF5": 110
  },
  {
    "name": "IN-08",
    "TMIN": 64.04,
    "WDF5": 10
  },
  {
    "name": "IN-08",
    "TMIN": 69.98,
    "WDF5": 0
  },
  {
    "name": "IN-08",
    "TMIN": 69.08,
    "WDF5": 0
  },
  {
    "name": "IN-08",
    "TMIN": 69.08,
    "WDF5": 170
  },
  {
    "name": "IN-08",
    "TMIN": 69.08,
    "WDF5": 240
  },
  {
    "name": "IN-08",
    "TMIN": 57.02,
    "WDF5": 200
  },
  {
    "name": "IN-08",
    "TMIN": 68,
    "WDF5": 10
  },
  {
    "name": "IN-08",
    "TMIN": 64.94,
    "WDF5": 0
  },
  {
    "name": "IN-08",
    "TMIN": 68,
    "WDF5": 240
  },
  {
    "name": "IN-08",
    "TMIN": 57.92,
    "WDF5": 290
  },
  {
    "name": "IN-08",
    "TMIN": 77,
    "WDF5": 240
  },
  {
    "name": "IN-08",
    "TMIN": 71.06,
    "WDF5": 320
  },
  {
    "name": "IN-08",
    "TMIN": 69.08,
    "WDF5": 90
  },
  {
    "name": "IN-08",
    "TMIN": 75.92,
    "WDF5": 180
  },
  {
    "name": "IN-08",
    "TMIN": 55.04,
    "WDF5": 220
  },
  {
    "name": "IN-08",
    "TMIN": 69.98,
    "WDF5": 210
  },
  {
    "name": "IN-08",
    "TMIN": 73.94,
    "WDF5": 210
  },
  {
    "name": "IN-08",
    "TMIN": 69.98,
    "WDF5": 220
  },
  {
    "name": "IN-08",
    "TMIN": 66.02,
    "WDF5": 350
  },
  {
    "name": "IN-08",
    "TMIN": 60.08,
    "WDF5": 0
  },
  {
    "name": "IN-08",
    "TMIN": 69.98,
    "WDF5": 330
  },
  {
    "name": "IN-08",
    "TMIN": 66.02,
    "WDF5": 220
  },
  {
    "name": "IN-08",
    "TMIN": 66.92,
    "WDF5": 160
  },
  {
    "name": "IN-08",
    "TMIN": 64.94,
    "WDF5": 10
  },
  {
    "name": "IN-08",
    "TMIN": 60.98,
    "WDF5": 220
  },
  {
    "name": "IN-08",
    "TMIN": 69.08,
    "WDF5": 220
  },
  {
    "name": "IN-08",
    "TMIN": 57.92,
    "WDF5": 20
  },
  {
    "name": "MS-02",
    "TMIN": 33.08,
    "WDF5": 310
  },
  {
    "name": "MS-02",
    "TMIN": 57.92,
    "WDF5": 170
  },
  {
    "name": "MS-02",
    "TMIN": 44.06,
    "WDF5": 330
  },
  {
    "name": "MS-02",
    "TMIN": 66.02,
    "WDF5": 150
  },
  {
    "name": "MS-02",
    "TMIN": 29.12,
    "WDF5": 260
  },
  {
    "name": "MS-02",
    "TMIN": 42.08,
    "WDF5": 280
  },
  {
    "name": "MS-02",
    "TMIN": 30.2,
    "WDF5": 190
  },
  {
    "name": "MS-02",
    "TMIN": 26.24,
    "WDF5": 360
  },
  {
    "name": "MS-02",
    "TMIN": 37.94,
    "WDF5": 220
  },
  {
    "name": "MS-02",
    "TMIN": 62.06,
    "WDF5": 220
  },
  {
    "name": "MS-02",
    "TMIN": 62.96,
    "WDF5": 160
  },
  {
    "name": "MS-02",
    "TMIN": 46.04,
    "WDF5": 200
  },
  {
    "name": "MS-02",
    "TMIN": 30.2,
    "WDF5": 330
  },
  {
    "name": "MS-02",
    "TMIN": 37.04,
    "WDF5": 230
  },
  {
    "name": "MS-02",
    "TMIN": 42.98,
    "WDF5": 270
  },
  {
    "name": "MS-02",
    "TMIN": 29.12,
    "WDF5": 100
  },
  {
    "name": "MS-02",
    "TMIN": 31.1,
    "WDF5": 200
  },
  {
    "name": "MS-02",
    "TMIN": 39.02,
    "WDF5": 270
  },
  {
    "name": "MS-02",
    "TMIN": 51.98,
    "WDF5": 280
  },
  {
    "name": "MS-02",
    "TMIN": 33.98,
    "WDF5": 210
  },
  {
    "name": "MS-02",
    "TMIN": 0,
    "WDF5": 170
  },
  {
    "name": "MS-02",
    "TMIN": 62.06,
    "WDF5": 150
  },
  {
    "name": "MS-02",
    "TMIN": 57.02,
    "WDF5": 160
  },
  {
    "name": "MS-02",
    "TMIN": 35.96,
    "WDF5": 10
  },
  {
    "name": "MS-02",
    "TMIN": 60.98,
    "WDF5": 220
  },
  {
    "name": "MS-02",
    "TMIN": 29.12,
    "WDF5": 320
  },
  {
    "name": "MS-02",
    "TMIN": 39.02,
    "WDF5": 110
  },
  {
    "name": "MS-02",
    "TMIN": 26.24,
    "WDF5": 150
  },
  {
    "name": "MS-02",
    "TMIN": 62.96,
    "WDF5": 150
  },
  {
    "name": "MS-02",
    "TMIN": 29.12,
    "WDF5": 10
  }
]