[
  {
    "name": "TX-01",
    "PRCP": 0.09843,
    "SNWD": 1.1811
  },
  {
    "name": "TX-01",
    "PRCP": 0,
    "SNWD": 1.1811
  },
  {
    "name": "TX-01",
    "PRCP": 0,
    "SNWD": 0
  },
  {
    "name": "GA-03",
    "PRCP": 0,
    "SNWD": 0
  },
  {
    "name": "GA-03",
    "PRCP": 0,
    "SNWD": 0
  },
  {
    "name": "GA-03",
    "PRCP": 0,
    "SNWD": 0
  },
  {
    "name": "NE-02",
    "PRCP": 0.01181,
    "SNWD": 3.14961
  },
  {
    "name": "NE-02",
    "PRCP": 0,
    "SNWD": 1.1811
  },
  {
    "name": "NE-02",
    "PRCP": 0,
    "SNWD": 0
  }
]