[
  {
    "name": "MI-12",
    "TMAX": 30.2,
    "WDF5": 230
  },
  {
    "name": "MI-12",
    "TMAX": 26.24,
    "WDF5": 290
  },
  {
    "name": "MI-12",
    "TMAX": 33.08,
    "WDF5": 270
  },
  {
    "name": "CO-11",
    "TMAX": 66.02,
    "WDF5": 20
  },
  {
    "name": "CO-11",
    "TMAX": 62.06,
    "WDF5": 280
  },
  {
    "name": "CO-11",
    "TMAX": 82.04,
    "WDF5": 330
  },
  {
    "name": "LA-03",
    "TMAX": 60.98,
    "WDF5": 10
  },
  {
    "name": "LA-03",
    "TMAX": 75.02,
    "WDF5": 90
  },
  {
    "name": "LA-03",
    "TMAX": 73.04,
    "WDF5": 360
  },
  {
    "name": "IA-10",
    "TMAX": 60.08,
    "WDF5": 310
  },
  {
    "name": "IA-10",
    "TMAX": 80.96,
    "WDF5": 190
  },
  {
    "name": "IA-10",
    "TMAX": 71.06,
    "WDF5": 330
  },
  {
    "name": "SC-05",
    "TMAX": 82.94,
    "WDF5": 50
  },
  {
    "name": "SC-05",
    "TMAX": 89.96,
    "WDF5": 140
  },
  {
    "name": "SC-05",
    "TMAX": 75.92,
    "WDF5": 230
  },
  {
    "name": "ME-02",
    "TMAX": 41,
    "WDF5": 150
  },
  {
    "name": "ME-02",
    "TMAX": 35.06,
    "WDF5": 310
  },
  {
    "name": "ME-02",
    "TMAX": 33.98,
    "WDF5": 170
  },
  {
    "name": "IN-07",
    "TMAX": 73.94,
    "WDF5": 100
  },
  {
    "name": "IN-07",
    "TMAX": 91.04,
    "WDF5": 270
  },
  {
    "name": "IN-07",
    "TMAX": 86,
    "WDF5": 320
  },
  {
    "name": "UT-03",
    "TMAX": 0,
    "WDF5": 240
  },
  {
    "name": "UT-03",
    "TMAX": 57.02,
    "WDF5": 230
  },
  {
    "name": "UT-03",
    "TMAX": 51.98,
    "WDF5": 250
  },
  {
    "name": "IL-03",
    "TMAX": 46.94,
    "WDF5": 90
  },
  {
    "name": "IL-03",
    "TMAX": 41,
    "WDF5": 330
  },
  {
    "name": "IL-03",
    "TMAX": 64.94,
    "WDF5": 250
  },
  {
    "name": "DE-03",
    "TMAX": 75.92,
    "WDF5": 210
  },
  {
    "name": "DE-03",
    "TMAX": 51.08,
    "WDF5": 280
  },
  {
    "name": "DE-03",
    "TMAX": 60.08,
    "WDF5": 220
  }
]